Metadata-Version: 2.1
Name: organizator1
Version: 0.0.2
Summary: just playing
Home-page: UNKNOWN
Author: pk
Author-email: kali.thot@centrum.cz
License: UNKNOWN
Platform: UNKNOWN
